{
  "provider": "github-oauth",
  "provider_version": "2022-11-28",
  "sdk": {
    "name": "oauth-http-client",
    "version": "node-24-fetch"
  },
  "source": {
    "type": "docs",
    "title": "GitHub REST API authentication",
    "url_or_path": "https://docs.github.com/rest/authentication/authenticating-to-the-rest-api",
    "retrieved_at": "2026-05-26"
  },
  "scenario": "expired_token",
  "request": {
    "method": "GET",
    "path": "/user",
    "headers": {
      "Authorization": "Bearer unknown"
    },
    "body": {}
  },
  "response": {
    "status": 401,
    "headers": {
      "Content-Type": "application/json"
    },
    "body": {
      "message": "Bad credentials",
      "documentation_url": "https://docs.github.com/rest",
      "status": "Unauthorized"
    }
  },
  "normalization": [
    "token is deterministic fake invalid data",
    "response uses common public REST error fields",
    "no external GitHub calls are made"
  ]
}
